AUTHORS
LICENSE
MANIFEST.in
README.md
setup.py
ironeagle/VERSION
ironeagle/__init__.py
ironeagle.egg-info/PKG-INFO
ironeagle.egg-info/SOURCES.txt
ironeagle.egg-info/dependency_links.txt
ironeagle.egg-info/requires.txt
ironeagle.egg-info/top_level.txt
tests/__init__.py
tests/test_dataframe_io.py