Metadata-Version: 1.1
Name: ironeagle
Version: 0.4
Summary: Helper library for working with Pandas and the Cassandra Native Driver
Home-page: https://github.com/rustyrazorblade/ironeagle
Author: Jon Haddad
Author-email: jon@jonhaddad.com
License: BSD
Keywords: cassandra,cql,pandas
Platform: UNKNOWN
Classifier: License :: OSI Approved :: BSD License
Classifier: Operating System :: OS Independent
Classifier: Programming Language :: Python :: 2.7
Classifier: Topic :: Software Development :: Libraries :: Python Modules
Classifier: Topic :: Database
